pySMART/__init__.py
pySMART/attribute.py
pySMART/device.py
pySMART/device_list.py
pySMART/test_entry.py
pySMART/utils.py
pySMART.smartx-0.3.10.dist-info/METADATA
pySMART.smartx-0.3.10.dist-info/WHEEL
pySMART.smartx-0.3.10.dist-info/top_level.txt
pySMART.smartx-0.3.10.dist-info/RECORD
