Metadata-Version: 2.1
Name: pySMART.smartx
Version: 0.3.10
Summary: Wrapper for smartctl (smartmontools)
Home-page: https://github.com/smartxworks/pySMART
Author: Marc Herndon
Author-email: Herndon.MarcT@gmail.com
License: GNU GPLv2
Platform: UNKNOWN
